{
  "project_info": {
    "project_number": "451722740141",
    "firebase_url": "https://art-gallery-96bdb-default-rtdb.asia-southeast1.firebasedatabase.app",
    "project_id": "art-gallery-96bdb",
    "storage_bucket": "art-gallery-96bdb.appspot.com"
  },
  "client": [
    {
      "client_info": {
        "mobilesdk_app_id": "1:451722740141:android:b467cc5e81d30b22496124",
        "android_client_info": {
          "package_name": "com.artgalleryapp"
        }
      },
      "oauth_client": [
        {
          "client_id": "451722740141-l3n9u55370hdr95j2tg6vt4hr1qj1u73.apps.googleusercontent.com",
          "client_type": 1,
          "android_info": {
            "package_name": "com.artgalleryapp",
            "certificate_hash": "5e8f16062ea3cd2c4a0d547876baa6f38cabf625"
          }
        },
        {
          "client_id": "451722740141-a4acj85ptbp6vlnm2vkt3mohsn4n4nsh.apps.googleusercontent.com",
          "client_type": 3
        }
      ],
      "api_key": [
        {
          "current_key": "AIzaSyANu_z7kqq77rQvnhmdoiSJLXp6s1Ei_NE"
        }
      ],
      "services": {
        "appinvite_service": {
          "other_platform_oauth_client": [
            {
              "client_id": "451722740141-a4acj85ptbp6vlnm2vkt3mohsn4n4nsh.apps.googleusercontent.com",
              "client_type": 3
            }
          ]
        }
      }
    }
  ],
  "configuration_version": "1"
}